{
  "title": "Gazzetta Ufficiale - Serie Generale - Sommario",
  "link": "http://www.gazzettaufficiale.it/eli/gu/2025/01/28/22/SG/html",
  "description": "Gazzetta Ufficiale - Serie Generale n. 22 del 28-01-2025",
  "language": "it",
  "generator": "",
  "published": "",
  "entries": [
    {
      "id": "jhkfoz-1738091481000",
      "title": "DECRETO DEL PRESIDENTE DELLA REPUBBLICA 15 gennaio 2025",
      "link": "http://www.gazzettaufficiale.it/eli/id/2025/01/28/25A00467/SG",
      "published": "2025-01-28T19:11:21.000Z",
      "description": "Scioglimento del consiglio comunale di Genova. (25A00467)"
    },
    {
      "id": "jhl2oi-1738091482000",
      "title": "DECRETO DEL PRESIDENTE DELLA REPUBBLICA 15 gennaio 2025",
      "link": "http://www.gazzettaufficiale.it/eli/id/2025/01/28/25A00468/SG",
      "published": "2025-01-28T19:11:22.000Z",
      "description": "Scioglimento del consiglio comunale di Cascinette  d'Ivrea  e  nomina del commissario straordinario. (25A00468)"
    },
    {
      "id": "jhlpo1-1738091482000",
      "title": "DECRETO DEL PRESIDENTE DELLA REPUBBLICA 15 gennaio 2025",
      "link": "http://www.gazzettaufficiale.it/eli/id/2025/01/28/25A00469/SG",
      "published": "2025-01-28T19:11:22.000Z",
      "description": "Scioglimento  del  consiglio  comunale  di  Sulmona  e   nomina   del commissario straordinario. (25A00469)"
    },
    {
      "id": "ji3lat-1738091485000",
      "title": "DECRETO DEL PRESIDENTE DELLA REPUBBLICA 15 gennaio 2025",
      "link": "http://www.gazzettaufficiale.it/eli/id/2025/01/28/25A00476/SG",
      "published": "2025-01-28T19:11:25.000Z",
      "description": "Scioglimento del consiglio comunale di Santa Maria di Sala  e  nomina del commissario straordinario. (25A00476)"
    },
    {
      "id": "ji48ac-1738091485000",
      "title": "DECRETO DEL PRESIDENTE DELLA REPUBBLICA 15 gennaio 2025",
      "link": "http://www.gazzettaufficiale.it/eli/id/2025/01/28/25A00477/SG",
      "published": "2025-01-28T19:11:25.000Z",
      "description": "Scioglimento  del  consiglio  comunale  di  Scalea   e   nomina   del commissario straordinario. (25A00477)"
    },
    {
      "id": "jhzrdn-1738091483000",
      "title": "MINISTERO DELLA SALUTE - DECRETO 17 gennaio 2025",
      "link": "http://www.gazzettaufficiale.it/eli/id/2025/01/28/25A00470/SG",
      "published": "2025-01-28T19:11:23.000Z",
      "description": "Sospensione  della  validita'  del  decreto  1°  ottobre   2020,   di indicazioni per le etichette dell'acqua minerale naturale «Vitasana», in Comune di Feroleto Antico. (25A00470)"
    },
    {
      "id": "ji11cp-1738091483000",
      "title": "MINISTERO DELLA SALUTE - DECRETO 17 gennaio 2025",
      "link": "http://www.gazzettaufficiale.it/eli/id/2025/01/28/25A00472/SG",
      "published": "2025-01-28T19:11:23.000Z",
      "description": "Indicazioni per le etichette dell'acqua minerale naturale «Acqua  San Carlo dr Zonder», Comune di Massa. (25A00472)"
    },
    {
      "id": "ji1oc8-1738091484000",
      "title": "MINISTERO DELLA SALUTE - DECRETO 17 gennaio 2025",
      "link": "http://www.gazzettaufficiale.it/eli/id/2025/01/28/25A00473/SG",
      "published": "2025-01-28T19:11:24.000Z",
      "description": "Ripristino della validita' del decreto di  riconoscimento  dell'acqua minerale naturale «Benaglia», nel Comune di Lazise. (25A00473)"
    },
    {
      "id": "ji0ed6-1738091483000",
      "title": "MINISTERO DELLE IMPRESE E DEL MADE IN ITALY - DECRETO 10 gennaio 2025",
      "link": "http://www.gazzettaufficiale.it/eli/id/2025/01/28/25A00471/SG",
      "published": "2025-01-28T19:11:23.000Z",
      "description": "Scioglimento della «Cooperativa sociale Assistenza Amica», in Cosenza e nomina del commissario liquidatore. (25A00471)"
    },
    {
      "id": "jyk54l-1738091486000",
      "title": "AGENZIA ITALIANA DEL FARMACO - DETERMINA 22 gennaio 2025",
      "link": "http://www.gazzettaufficiale.it/eli/id/2025/01/28/25A00564/SG",
      "published": "2025-01-28T19:11:26.000Z",
      "description": "Diniego del rinnovo dell'autorizzazione all'immissione  in  commercio del medicinale per  uso  umano  «Vulpur».  (Determina  n.  147/2025). (25A00564)"
    },
    {
      "id": "kcacz3-1738091487000",
      "title": "GARANTE PER LA PROTEZIONE DEI DATI PERSONALI - DELIBERA 27 novembre 2024",
      "link": "http://www.gazzettaufficiale.it/eli/id/2025/01/28/25A00603/SG",
      "published": "2025-01-28T19:11:27.000Z",
      "description": "Adozione del regolamento per la disciplina dei contratti  di  appalto dell'Ufficio del Garante aventi importo inferiore alle soglie europee e dell'unito regolamento. (Delibera n. 836). (25A00603)"
    },
    {
      "id": "jerjrl-1738091479000",
      "title": "AGENZIA ITALIANA DEL FARMACO - COMUNICATO",
      "link": "http://www.gazzettaufficiale.it/eli/id/2025/01/28/25A00414/SG",
      "published": "2025-01-28T19:11:19.000Z",
      "description": "Autorizzazione all'importazione  parallela  del  medicinale  per  uso umano «Xanax». (25A00414)"
    },
    {
      "id": "jes6r4-1738091480000",
      "title": "AGENZIA ITALIANA DEL FARMACO - COMUNICATO",
      "link": "http://www.gazzettaufficiale.it/eli/id/2025/01/28/25A00415/SG",
      "published": "2025-01-28T19:11:20.000Z",
      "description": "Autorizzazione all'importazione  parallela  del  medicinale  per  uso umano «Diane». (25A00415)"
    },
    {
      "id": "jestqn-1738091480000",
      "title": "AGENZIA ITALIANA DEL FARMACO - COMUNICATO",
      "link": "http://www.gazzettaufficiale.it/eli/id/2025/01/28/25A00416/SG",
      "published": "2025-01-28T19:11:20.000Z",
      "description": "Autorizzazione all'importazione  parallela  del  medicinale  per  uso umano «Opdivo». (25A00416)"
    },
    {
      "id": "ji2bbr-1738091484000",
      "title": "AGENZIA ITALIANA DEL FARMACO - COMUNICATO",
      "link": "http://www.gazzettaufficiale.it/eli/id/2025/01/28/25A00474/SG",
      "published": "2025-01-28T19:11:24.000Z",
      "description": "Autorizzazione all'immissione in commercio  del  medicinale  per  uso umano  «Efluelda»,  vaccino  influenzale  trivalente  (virioni  split inattivati). (25A00474)"
    },
    {
      "id": "ji2yba-1738091484000",
      "title": "AGENZIA ITALIANA DEL FARMACO - COMUNICATO",
      "link": "http://www.gazzettaufficiale.it/eli/id/2025/01/28/25A00475/SG",
      "published": "2025-01-28T19:11:24.000Z",
      "description": "Autorizzazione all'immissione in commercio  del  medicinale  per  uso umano «Vaxigrip», vaccino  antinfluenzale  trivalente  preparato  con virus frammentati «split», inattivati. (25A00475)"
    },
    {
      "id": "jfd9bj-1738091481000",
      "title": "MINISTERO DEGLI AFFARI ESTERI E DELLA COOPERAZIONE INTERNAZIONALE - COMUNICATO",
      "link": "http://www.gazzettaufficiale.it/eli/id/2025/01/28/25A00427/SG",
      "published": "2025-01-28T19:11:21.000Z",
      "description": "Limitazione delle funzioni del titolare  del  Consolato  onorario  in Norimberga (Germania). (25A00427)"
    },
    {
      "id": "jfdwb2-1738091481000",
      "title": "MINISTERO DEGLI AFFARI ESTERI E DELLA COOPERAZIONE INTERNAZIONALE - COMUNICATO",
      "link": "http://www.gazzettaufficiale.it/eli/id/2025/01/28/25A00428/SG",
      "published": "2025-01-28T19:11:21.000Z",
      "description": "Istituzione del Vice Consolato onorario a Manta (Ecuador). (25A00428)"
    },
    {
      "id": "jyks44-1738091486000",
      "title": "PROVINCIA AUTONOMA DI BOLZANO ALTO ADIGE - COMUNICATO",
      "link": "http://www.gazzettaufficiale.it/eli/id/2025/01/28/25A00565/SG",
      "published": "2025-01-28T19:11:26.000Z",
      "description": "Scioglimento, per atto dell'autorita',  della  cooperativa  «Progetto Artisti», in  Bolzano,  senza  nomina  del  commissario  liquidatore. (25A00565)"
    }
  ]
}