{
  "title": "Gazzetta Ufficiale - Serie Generale - Sommario",
  "link": "http://www.gazzettaufficiale.it/eli/gu/2024/11/23/275/SG/html",
  "description": "Gazzetta Ufficiale - Serie Generale n. 275 del 23-11-2024",
  "language": "it",
  "generator": "",
  "published": "",
  "entries": [
    {
      "id": "rxhsux-1732360081000",
      "title": "MINISTERO DELLA CULTURA - DECRETO 13 novembre 2024",
      "link": "http://www.gazzettaufficiale.it/eli/id/2024/11/23/24A06166/SG",
      "published": "2024-11-23T11:08:01.000Z",
      "description": "Dichiarazione di notevole interesse pubblico del  contesto  «Tiati  - Teanum Apulum - Civitate e Bassa Valle del Fortore». (24A06166)"
    },
    {
      "id": "rxj2tz-1732360081000",
      "title": "MINISTERO DELLA SALUTE - DECRETO 6 novembre 2024",
      "link": "http://www.gazzettaufficiale.it/eli/id/2024/11/23/24A06168/SG",
      "published": "2024-11-23T11:08:01.000Z",
      "description": "Individuazione delle aree tematiche «oncologia», «gastroenterologia», «cardiologia-pneumologia», «geriatria», «neurologia»,  «ostetricia  e ginecologia»,  per  la  «Fondazione  Policlinico   Universitario   A. Gemelli», in Roma. (24A06168)"
    },
    {
      "id": "rxjpti-1732360081000",
      "title": "MINISTERO DELLA SALUTE - DECRETO 6 novembre 2024",
      "link": "http://www.gazzettaufficiale.it/eli/id/2024/11/23/24A06169/SG",
      "published": "2024-11-23T11:08:01.000Z",
      "description": "Individuazione  delle   aree   tematiche   «cardiologia-pneumologia», «oncologia»,    «ematologia     e     immunologia»,     «neurologia», «gastroenterologia», «ostetricia e ginecologia»,  e  «trapiantologia» per la Fondazione IRCCS Ca'  Granda ..."
    },
    {
      "id": "ry2vfc-1732360082000",
      "title": "MINISTERO DELLE INFRASTRUTTURE E DEI TRASPORTI COMANDO GENERALE DEL CORPO DELLE CAPITANERIE DI PORTO - DECRETO 12 novembre 2024",
      "link": "http://www.gazzettaufficiale.it/eli/id/2024/11/23/24A06178/SG",
      "published": "2024-11-23T11:08:02.000Z",
      "description": "Autorizzazione all'organismo  ITALCERT  S.r.l.  all'espletamento  dei compiti di cui all'articolo 10, comma 4, del decreto  del  Presidente della Repubblica 6 giugno 2005, n. 134. (24A06178)"
    },
    {
      "id": "rxifug-1732360081000",
      "title": "PRESIDENZA DEL CONSIGLIO DEI MINISTRI - COMMISSARIO STRAORDINARIO DI GOVERNO PER IL GIUBILEO DELLA CHIESA CATTOLICA 2025 - ORDINANZA 11 novembre 2024",
      "link": "http://www.gazzettaufficiale.it/eli/id/2024/11/23/24A06167/SG",
      "published": "2024-11-23T11:08:01.000Z",
      "description": "Realizzazione  del  Polo  impiantistico  di  Roma  Capitale:   deroga all'art. 15, comma 1, della legge Regione Lazio n. 15 dell'11  agosto 2008 e s.m.i. e all'art. 31, comma  3,  del  decreto  del  Presidente della Repubblica n. 380 del 6 giugno..."
    },
    {
      "id": "ry1lga-1732360081000",
      "title": "PRESIDENZA DEL CONSIGLIO DEI MINISTRI - COMMISSARIO STRAORDINARIO DI GOVERNO PER IL GIUBILEO DELLA CHIESA CATTOLICA 2025 - ORDINANZA 15 novembre 2024",
      "link": "http://www.gazzettaufficiale.it/eli/id/2024/11/23/24A06176/SG",
      "published": "2024-11-23T11:08:01.000Z",
      "description": "Programma dettagliato degli  interventi  del  Giubileo  della  Chiesa cattolica 2025, approvato con decreto del  Presidente  del  Consiglio dei ministri 11  giugno  2024  -  Art.  9,  comma  1,  lettera  b)  - Intervento ID  n.  249  recante ..."
    },
    {
      "id": "ry28ft-1732360081000",
      "title": "PRESIDENZA DEL CONSIGLIO DEI MINISTRI - COMMISSARIO STRAORDINARIO DI GOVERNO PER IL GIUBILEO DELLA CHIESA CATTOLICA 2025 - ORDINANZA 15 novembre 2024",
      "link": "http://www.gazzettaufficiale.it/eli/id/2024/11/23/24A06177/SG",
      "published": "2024-11-23T11:08:01.000Z",
      "description": "Giubileo 2025 -  Intervento  123  «Parcheggio  interrato  Lungotevere Castello». (Ordinanza n. 43). (24A06177)"
    },
    {
      "id": "ry3iev-1732360082000",
      "title": "AGENZIA ITALIANA DEL FARMACO - COMUNICATO",
      "link": "http://www.gazzettaufficiale.it/eli/id/2024/11/23/24A06179/SG",
      "published": "2024-11-23T11:08:02.000Z",
      "description": "Modifica  dell'autorizzazione   all'immissione   in   commercio   del medicinale per uso  umano,  a  base  di  colecalciferolo,  «Xarenel». (24A06179)"
    },
    {
      "id": "ryhk4h-1732360082000",
      "title": "AGENZIA ITALIANA DEL FARMACO - COMUNICATO",
      "link": "http://www.gazzettaufficiale.it/eli/id/2024/11/23/24A06180/SG",
      "published": "2024-11-23T11:08:02.000Z",
      "description": "Autorizzazione all'immissione in commercio  del  medicinale  per  uso umano, a base di sildenafil, «Balcoga» (24A06180)"
    },
    {
      "id": "ryi740-1732360082000",
      "title": "AGENZIA ITALIANA DEL FARMACO - COMUNICATO",
      "link": "http://www.gazzettaufficiale.it/eli/id/2024/11/23/24A06181/SG",
      "published": "2024-11-23T11:08:02.000Z",
      "description": "Modifica  dell'autorizzazione   all'immissione   in   commercio   del medicinale  per  uso  umano,  a  base  di   quetiapina,   «Seroquel». (24A06181)"
    },
    {
      "id": "ryiu3j-1732360082000",
      "title": "AGENZIA ITALIANA DEL FARMACO - COMUNICATO",
      "link": "http://www.gazzettaufficiale.it/eli/id/2024/11/23/24A06182/SG",
      "published": "2024-11-23T11:08:02.000Z",
      "description": "Modifica dell'autorizzazione all'immissione in  commercio  di  taluni medicinali per uso umano, a base di glucosio  monoidrato  e  potassio cloruro, sodio cloruro e potassio cloruro. (24A06182)"
    },
    {
      "id": "rymo0p-1732360083000",
      "title": "ISTITUTO NAZIONALE DI STATISTICA - COMUNICATO",
      "link": "http://www.gazzettaufficiale.it/eli/id/2024/11/23/24A06188/SG",
      "published": "2024-11-23T11:08:03.000Z",
      "description": "Indici dei prezzi al consumo per le famiglie di operai  e  impiegati, relativi al  mese  di  ottobre  2024,  che  si  pubblicano  ai  sensi dell'art. 81 della legge 27 luglio 1978,  n.  392  (Disciplina  delle locazioni di immobili urbani), ed ai..."
    },
    {
      "id": "rykr24-1732360083000",
      "title": "MINISTERO DELL'INTERNO - COMUNICATO",
      "link": "http://www.gazzettaufficiale.it/eli/id/2024/11/23/24A06185/SG",
      "published": "2024-11-23T11:08:03.000Z",
      "description": "Classificazione di un prodotto esplosivo (24A06185)"
    },
    {
      "id": "ryle1n-1732360083000",
      "title": "MINISTERO DELL'INTERNO - COMUNICATO",
      "link": "http://www.gazzettaufficiale.it/eli/id/2024/11/23/24A06186/SG",
      "published": "2024-11-23T11:08:03.000Z",
      "description": "Classificazione di un prodotto esplosivo. (24A06186)"
    },
    {
      "id": "rym116-1732360083000",
      "title": "MINISTERO DELL'INTERNO - COMUNICATO",
      "link": "http://www.gazzettaufficiale.it/eli/id/2024/11/23/24A06187/SG",
      "published": "2024-11-23T11:08:03.000Z",
      "description": "Classificazione di un prodotto esplosivo (24A06187)"
    },
    {
      "id": "ryjh32-1732360082000",
      "title": "MINISTERO DELLA DIFESA - COMUNICATO",
      "link": "http://www.gazzettaufficiale.it/eli/id/2024/11/23/24A06183/SG",
      "published": "2024-11-23T11:08:02.000Z",
      "description": "Decreto di espunzione relativo agli alloggi da alienare (24A06183)"
    },
    {
      "id": "ryk42l-1732360083000",
      "title": "MINISTERO DELLE INFRASTRUTTURE E DEI TRASPORTI - COMUNICATO",
      "link": "http://www.gazzettaufficiale.it/eli/id/2024/11/23/24A06184/SG",
      "published": "2024-11-23T11:08:03.000Z",
      "description": "Rinnovo dell'autorizzazione della societa'  ECO  European  Certifying Organization S.p.a., con sede in  Via  Mengolina  33,  Faenza,  quale Organismo notificato per la certificazione dei recipienti a pressione trasportabili ai sensi del d.lgs. 12..."
    }
  ]
}