{
  "title": "Gazzetta Ufficiale - Serie Generale - Sommario",
  "link": "http://www.gazzettaufficiale.it/eli/gu/2024/10/08/236/SG/html",
  "description": "Gazzetta Ufficiale - Serie Generale n. 236 del 08-10-2024",
  "language": "it",
  "generator": "",
  "published": "",
  "entries": [
    {
      "id": "phs0ii-1728417368000",
      "title": "LEGGE 7 ottobre 2024, n.143",
      "link": "http://www.gazzettaufficiale.it/eli/id/2024/10/08/24G00161/SG",
      "published": "2024-10-08T19:56:08.000Z",
      "description": "Conversione in legge, con modificazioni, del decreto-legge  9  agosto 2024, n. 113, recante misure urgenti di carattere  fiscale,  proroghe di termini normativi ed interventi di carattere economico. (24G00161)"
    },
    {
      "id": "elhema-1728417341000",
      "title": "MINISTERO DELLA SALUTE - DECRETO 25 settembre 2024",
      "link": "http://www.gazzettaufficiale.it/eli/id/2024/10/08/24A05241/SG",
      "published": "2024-10-08T19:55:41.000Z",
      "description": "Requisiti   di   biosicurezza   per    stabilimenti    d'acquacoltura riconosciuti e di altre tipologie di  attivita'  ad  essi  correlate. (24A05241)"
    },
    {
      "id": "e541q5-1728417328000",
      "title": "MINISTERO DELLE IMPRESE E DEL MADE IN ITALY - DECRETO 20 settembre 2024",
      "link": "http://www.gazzettaufficiale.it/eli/id/2024/10/08/24A05158/SG",
      "published": "2024-10-08T19:55:28.000Z",
      "description": "Liquidazione  coatta   amministrativa   della   «L'Aliante   societa' cooperativa sociale», in Levate e nomina del commissario liquidatore. (24A05158)"
    },
    {
      "id": "e54opo-1728417329000",
      "title": "MINISTERO DELLE IMPRESE E DEL MADE IN ITALY - DECRETO 20 settembre 2024",
      "link": "http://www.gazzettaufficiale.it/eli/id/2024/10/08/24A05159/SG",
      "published": "2024-10-08T19:55:29.000Z",
      "description": "Liquidazione  coatta  amministrativa  della  «Pianetaverde   societa' cooperativa in liquidazione»,  in  Rende  e  nomina  del  commissario liquidatore. (24A05159)"
    },
    {
      "id": "e5iqfa-1728417330000",
      "title": "MINISTERO DELLE IMPRESE E DEL MADE IN ITALY - DECRETO 20 settembre 2024",
      "link": "http://www.gazzettaufficiale.it/eli/id/2024/10/08/24A05160/SG",
      "published": "2024-10-08T19:55:30.000Z",
      "description": "Liquidazione coatta amministrativa della «Progetto  Assistenza  Santa Rita societa' cooperativa sociale  o.n.l.u.s.  in  liquidazione»,  in Savona e nomina del commissario liquidatore. (24A05160)"
    },
    {
      "id": "eli1lt-1728417344000",
      "title": "MINISTERO DELLE IMPRESE E DEL MADE IN ITALY - DECRETO 20 settembre 2024",
      "link": "http://www.gazzettaufficiale.it/eli/id/2024/10/08/24A05242/SG",
      "published": "2024-10-08T19:55:44.000Z",
      "description": "Liquidazione coatta amministrativa della  «Cooperativa  sociale  Voce Amica  societa'  cooperativa»,  in  Reggio  Calabria  e  nomina   del commissario liquidatore. (24A05242)"
    },
    {
      "id": "eliolc-1728417345000",
      "title": "MINISTERO DELLE IMPRESE E DEL MADE IN ITALY - DECRETO 20 settembre 2024",
      "link": "http://www.gazzettaufficiale.it/eli/id/2024/10/08/24A05243/SG",
      "published": "2024-10-08T19:55:45.000Z",
      "description": "Sostituzione del commissario liquidatore della «Edilcoop soc. coop. a r.l.», in Ponte nelle Alpi, in  liquidazione  coatta  amministrativa. (24A05243)"
    },
    {
      "id": "eljyke-1728417347000",
      "title": "AGENZIA ITALIANA DEL FARMACO - DETERMINA 11 settembre 2024",
      "link": "http://www.gazzettaufficiale.it/eli/id/2024/10/08/24A05245/SG",
      "published": "2024-10-08T19:55:47.000Z",
      "description": "Riclassificazione del medicinale per uso umano  «Atorvastatina  Mylan Generics Italia», ai sensi dell'articolo 8, comma 10, della legge  24 dicembre 1993, n. 537. (Determina n. 490/2024). (24A05245)"
    },
    {
      "id": "elkljx-1728417348000",
      "title": "AGENZIA ITALIANA DEL FARMACO - DETERMINA 11 settembre 2024",
      "link": "http://www.gazzettaufficiale.it/eli/id/2024/10/08/24A05246/SG",
      "published": "2024-10-08T19:55:48.000Z",
      "description": "Riclassificazione del medicinale per uso umano  «Cluviat»,  ai  sensi dell'articolo 8, comma 10, della legge  24  dicembre  1993,  n.  537. (Determina n. 491/2024). (24A05246)"
    },
    {
      "id": "ell8jg-1728417350000",
      "title": "AGENZIA ITALIANA DEL FARMACO - DETERMINA 20 settembre 2024",
      "link": "http://www.gazzettaufficiale.it/eli/id/2024/10/08/24A05247/SG",
      "published": "2024-10-08T19:55:50.000Z",
      "description": "Riclassificazione del medicinale per  uso  umano  «Eylea»,  ai  sensi dell'articolo 8, comma 10, della legge  24  dicembre  1993,  n.  537. (Determina n. 502/2024). (24A05247)"
    },
    {
      "id": "ellviz-1728417351000",
      "title": "AGENZIA ITALIANA DEL FARMACO - DETERMINA 30 settembre 2024",
      "link": "http://www.gazzettaufficiale.it/eli/id/2024/10/08/24A05248/SG",
      "published": "2024-10-08T19:55:51.000Z",
      "description": "Aggiornamento della Nota AIFA 98 di cui alla determina n. 20/2024 del 25 gennaio 2024. (Determina n. 505/2024). (24A05248)"
    },
    {
      "id": "eje260-1728417339000",
      "title": "COMITATO INTERMINISTERIALE PER LA PROGRAMMAZIONE ECONOMICA E LO SVILUPPO SOSTENIBILE - DELIBERA 9 luglio 2024",
      "link": "http://www.gazzettaufficiale.it/eli/id/2024/10/08/24A05207/SG",
      "published": "2024-10-08T19:55:39.000Z",
      "description": "Sisma Abruzzo 2009 - Conservatorio statale di musica Alfredo  Casella - Comune dell'Aquila. Riprogrammazione  delle  risorse  di  cui  alla delibera CIPE n. 135 del 2012 e modifica delle delibere  CIPE  n.  44 del 2012 e n. 24 del 2018. (Delibera..."
    },
    {
      "id": "ejep5j-1728417340000",
      "title": "COMITATO INTERMINISTERIALE PER LA PROGRAMMAZIONE ECONOMICA E LO SVILUPPO SOSTENIBILE - DELIBERA 9 luglio 2024",
      "link": "http://www.gazzettaufficiale.it/eli/id/2024/10/08/24A05208/SG",
      "published": "2024-10-08T19:55:40.000Z",
      "description": "Sisma Abruzzo 2009 -  Programma  di  sviluppo  Restart  di  cui  alla delibera CIPE n. 49 del 2016. Assegnazione di  risorse  a  interventi gia' approvati, modifica del soggetto assegnatario e rimodulazione di un intervento gia' approvato...."
    },
    {
      "id": "eljbkv-1728417346000",
      "title": "COMITATO INTERMINISTERIALE PER LA PROGRAMMAZIONE ECONOMICA E LO SVILUPPO SOSTENIBILE - DELIBERA 9 luglio 2024",
      "link": "http://www.gazzettaufficiale.it/eli/id/2024/10/08/24A05244/SG",
      "published": "2024-10-08T19:55:46.000Z",
      "description": "FSC 2021-2027. Assegnazione di risorse per gli interventi di bonifica e risanamento ambientale e rigenerazione dell'area  denominata  «Zona Falcata» di Messina e individuazione del soggetto attuatore (articolo 5, comma 3-bis, decreto-legge n. ..."
    },
    {
      "id": "eoaajo-1728417356000",
      "title": "TESTO COORDINATO DEL DECRETO-LEGGE 9 agosto 2024, n.113",
      "link": "http://www.gazzettaufficiale.it/eli/id/2024/10/08/24A05294/SG",
      "published": "2024-10-08T19:55:56.000Z",
      "description": "Testo del decreto-legge 9 agosto 2024, n. 113, (in Gazzetta Ufficiale - Serie generale - n. 186 del 9 agosto 2024), coordinato con la legge di conversione 7 ottobre 2024, n.  143  (in  questa  stessa  Gazzetta Ufficiale, alla  pag.  1),  recante: ..."
    },
    {
      "id": "e7al42-1728417331000",
      "title": "AGENZIA ITALIANA DEL FARMACO - COMUNICATO",
      "link": "http://www.gazzettaufficiale.it/eli/id/2024/10/08/24A05197/SG",
      "published": "2024-10-08T19:55:31.000Z",
      "description": "Modifica  dell'autorizzazione   all'immissione   in   commercio   del medicinale per uso umano, a base di letrozolo, «Raziolet». (24A05197)"
    },
    {
      "id": "e7b83l-1728417332000",
      "title": "AGENZIA ITALIANA DEL FARMACO - COMUNICATO",
      "link": "http://www.gazzettaufficiale.it/eli/id/2024/10/08/24A05198/SG",
      "published": "2024-10-08T19:55:32.000Z",
      "description": "Modifica  dell'autorizzazione   all'immissione   in   commercio   del medicinale  per  uso  umano,  a  base  di  colecalciferolo  (vitamina D3 ), «Colecalciferolo Teva B.V». (24A05198)"
    },
    {
      "id": "e7bv34-1728417332000",
      "title": "AGENZIA ITALIANA DEL FARMACO - COMUNICATO",
      "link": "http://www.gazzettaufficiale.it/eli/id/2024/10/08/24A05199/SG",
      "published": "2024-10-08T19:55:32.000Z",
      "description": "Autorizzazione all'immissione in commercio  del  medicinale  per  uso umano, a base di melatonina, «Melatonina Viatris». (24A05199)"
    },
    {
      "id": "ej9l9b-1728417333000",
      "title": "AGENZIA ITALIANA DEL FARMACO - COMUNICATO",
      "link": "http://www.gazzettaufficiale.it/eli/id/2024/10/08/24A05200/SG",
      "published": "2024-10-08T19:55:33.000Z",
      "description": "Autorizzazione all'immissione in commercio  del  medicinale  per  uso umano, a base di xilometazolina cloridrato, «Rimet». (24A05200)"
    },
    {
      "id": "eja88u-1728417334000",
      "title": "AGENZIA ITALIANA DEL FARMACO - COMUNICATO",
      "link": "http://www.gazzettaufficiale.it/eli/id/2024/10/08/24A05201/SG",
      "published": "2024-10-08T19:55:34.000Z",
      "description": "Autorizzazione all'immissione in commercio  del  medicinale  per  uso umano, a base  di  perindopril  tert-butilamina/amlodipina  besilato, «Tenamper». (24A05201)"
    },
    {
      "id": "ejav8d-1728417335000",
      "title": "AGENZIA ITALIANA DEL FARMACO - COMUNICATO",
      "link": "http://www.gazzettaufficiale.it/eli/id/2024/10/08/24A05202/SG",
      "published": "2024-10-08T19:55:35.000Z",
      "description": "Autorizzazione all'immissione in commercio  del  medicinale  per  uso umano, a base di carbossimaltosio ferrico, «Carbossimaltosio  Ferrico Teva». (24A05202)"
    },
    {
      "id": "ejbi7w-1728417336000",
      "title": "AGENZIA ITALIANA DEL FARMACO - COMUNICATO",
      "link": "http://www.gazzettaufficiale.it/eli/id/2024/10/08/24A05203/SG",
      "published": "2024-10-08T19:55:36.000Z",
      "description": "Autorizzazione all'importazione  parallela  del  medicinale  per  uso umano «Zoely» (24A05203)"
    },
    {
      "id": "ejc57f-1728417337000",
      "title": "AGENZIA ITALIANA DEL FARMACO - COMUNICATO",
      "link": "http://www.gazzettaufficiale.it/eli/id/2024/10/08/24A05204/SG",
      "published": "2024-10-08T19:55:37.000Z",
      "description": "Modifica  dell'autorizzazione   all'immissione   in   commercio   del medicinale per uso umano, a base di amoxicillina, «Amox». (24A05204)"
    },
    {
      "id": "ejcs6y-1728417338000",
      "title": "AGENZIA ITALIANA DEL FARMACO - COMUNICATO",
      "link": "http://www.gazzettaufficiale.it/eli/id/2024/10/08/24A05205/SG",
      "published": "2024-10-08T19:55:38.000Z",
      "description": "Modifica  dell'autorizzazione   all'immissione   in   commercio   del medicinale  per  uso  umano,  a  base  di  ondansetron,  «Ondansetron Accord». (24A05205)"
    },
    {
      "id": "ejdf6h-1728417338000",
      "title": "AGENZIA ITALIANA DEL FARMACO - COMUNICATO",
      "link": "http://www.gazzettaufficiale.it/eli/id/2024/10/08/24A05206/SG",
      "published": "2024-10-08T19:55:38.000Z",
      "description": "Modifica  dell'autorizzazione   all'immissione   in   commercio   del medicinale per uso umano, a base di fibrinogeno umano, «Fibriclotte». (24A05206)"
    },
    {
      "id": "elmiii-1728417352000",
      "title": "AGENZIA ITALIANA DEL FARMACO - COMUNICATO",
      "link": "http://www.gazzettaufficiale.it/eli/id/2024/10/08/24A05249/SG",
      "published": "2024-10-08T19:55:52.000Z",
      "description": "Revoca, su rinuncia, dell'autorizzazione all'immissione in  commercio del medicinale per uso umano «Febuxostat Tillomed». (24A05249)"
    },
    {
      "id": "em0k84-1728417353000",
      "title": "AGENZIA ITALIANA DEL FARMACO - COMUNICATO",
      "link": "http://www.gazzettaufficiale.it/eli/id/2024/10/08/24A05250/SG",
      "published": "2024-10-08T19:55:53.000Z",
      "description": "Autorizzazione all'importazione parallela del medicinaleper uso umano «Lamictal» (24A05250)"
    },
    {
      "id": "em2h6p-1728417355000",
      "title": "CASSA DEPOSITI E PRESTITI S.P.A. - COMUNICATO",
      "link": "http://www.gazzettaufficiale.it/eli/id/2024/10/08/24A05253/SG",
      "published": "2024-10-08T19:55:55.000Z",
      "description": "Avviso a valere sui buoni fruttiferi postali (24A05253)"
    },
    {
      "id": "dq7oqt-1728417307000",
      "title": "COMMISSIONE DI GARANZIA DEGLI STATUTI E PER LA TRASPARENZA E IL CONTROLLO DEI RENDICONTI DEI PARTITI POLITICI - COMUNICATO",
      "link": "http://www.gazzettaufficiale.it/eli/id/2024/10/08/24A05095/SG",
      "published": "2024-10-08T19:55:07.000Z",
      "description": "Statuto del movimento politico «Forza Italia» (24A05095)"
    },
    {
      "id": "em177n-1728417354000",
      "title": "MINISTERO DEGLI AFFARI ESTERI E DELLA COOPERAZIONE INTERNAZIONALE - COMUNICATO",
      "link": "http://www.gazzettaufficiale.it/eli/id/2024/10/08/24A05251/SG",
      "published": "2024-10-08T19:55:54.000Z",
      "description": "Rilascio di exequatur (24A05251)"
    },
    {
      "id": "em1u76-1728417355000",
      "title": "MINISTERO DEGLI AFFARI ESTERI E DELLA COOPERAZIONE INTERNAZIONALE - COMUNICATO",
      "link": "http://www.gazzettaufficiale.it/eli/id/2024/10/08/24A05252/SG",
      "published": "2024-10-08T19:55:55.000Z",
      "description": "Rilascio di exequatur (24A05252)"
    }
  ]
}