{
  "title": "Gazzetta Ufficiale - Serie Generale - Sommario",
  "link": "http://www.gazzettaufficiale.it/eli/gu/2024/08/28/201/SG/html",
  "description": "Gazzetta Ufficiale - Serie Generale n. 201 del 28-08-2024",
  "language": "it",
  "generator": "",
  "published": "",
  "entries": [
    {
      "id": "z5uuz0-1724860348000",
      "title": "DECRETO DEL PRESIDENTE DELLA REPUBBLICA 31 luglio 2024",
      "link": "http://www.gazzettaufficiale.it/eli/id/2024/08/28/24A04386/SG",
      "published": "2024-08-28T15:52:28.000Z",
      "description": "Scioglimento del consiglio comunale di Irsina. (24A04386)"
    },
    {
      "id": "yqfcdu-1724860350000",
      "title": "DECRETO DEL PRESIDENTE DEL CONSIGLIO DEI MINISTRI 24 luglio 2024",
      "link": "http://www.gazzettaufficiale.it/eli/id/2024/08/28/24A04458/SG",
      "published": "2024-08-28T15:52:30.000Z",
      "description": "Definizione dei termini e delle modalita' per l'impiego del personale del Ministero della difesa presso  l'Agenzia  per  la  cybersicurezza nazionale. (24A04458)"
    },
    {
      "id": "z5yow6-1724860347000",
      "title": "DELIBERA DEL CONSIGLIO DEI MINISTRI 7 agosto 2024",
      "link": "http://www.gazzettaufficiale.it/eli/id/2024/08/28/24A04380/SG",
      "published": "2024-08-28T15:52:27.000Z",
      "description": "Proroga dello stato di emergenza  in  conseguenza  degli  eccezionali eventi meteorologici che  dal  13  luglio  al  6  agosto  2023  hanno interessato il territorio della Regione Veneto. (24A04380)"
    },
    {
      "id": "z5y1wn-1724860347000",
      "title": "DELIBERA DEL CONSIGLIO DEI MINISTRI 7 agosto 2024",
      "link": "http://www.gazzettaufficiale.it/eli/id/2024/08/28/24A04381/SG",
      "published": "2024-08-28T15:52:27.000Z",
      "description": "Proroga dello stato di emergenza  in  conseguenza  degli  eccezionali eventi meteorologici che a partire dal 4  al  31  luglio  2023  hanno interessato il territorio della Regione Lombardia. (24A04381)"
    },
    {
      "id": "z5xex4-1724860347000",
      "title": "DELIBERA DEL CONSIGLIO DEI MINISTRI 7 agosto 2024",
      "link": "http://www.gazzettaufficiale.it/eli/id/2024/08/28/24A04382/SG",
      "published": "2024-08-28T15:52:27.000Z",
      "description": "Dichiarazione  dello  stato  di  emergenza   in   conseguenza   degli eccezionali eventi meteorologici  verificatisi  nei  territori  della Citta' metropolitana di Milano e  delle  Province  di  Cremona  e  di Mantova nei giorni dal 15 al 25 maggio..."
    },
    {
      "id": "z5wrxl-1724860348000",
      "title": "DELIBERA DEL CONSIGLIO DEI MINISTRI 7 agosto 2024",
      "link": "http://www.gazzettaufficiale.it/eli/id/2024/08/28/24A04383/SG",
      "published": "2024-08-28T15:52:28.000Z",
      "description": "Dichiarazione  dello  stato  di  emergenza   in   conseguenza   degli eccezionali eventi meteorologici verificatisi  nei  giorni  29  e  30 giugno 2024 nel territorio dei Comuni  di  Balme,  di  Banchette,  di Bardonecchia, di Busano, di Cafasse,..."
    },
    {
      "id": "z5w4y2-1724860348000",
      "title": "DELIBERA DEL CONSIGLIO DEI MINISTRI 7 agosto 2024",
      "link": "http://www.gazzettaufficiale.it/eli/id/2024/08/28/24A04384/SG",
      "published": "2024-08-28T15:52:28.000Z",
      "description": "Proroga dello stato di emergenza  in  conseguenza  degli  eccezionali eventi meteorologici che il giorno 6 luglio 2023 hanno interessato il territorio della Provincia di Cuneo. (24A04384)"
    },
    {
      "id": "ys772m-1724860350000",
      "title": "MINISTERO DELL'AGRICOLTURA, DELLA SOVRANITA' ALIMENTARE E DELLE FORESTE - DECRETO 29 luglio 2024",
      "link": "http://www.gazzettaufficiale.it/eli/id/2024/08/28/24A04421/SG",
      "published": "2024-08-28T15:52:30.000Z",
      "description": "Posticipazione termini di presentazione delle domande di aiuto  della politica agricola comune per l'anno 2024. (24A04421)"
    },
    {
      "id": "yrkuj5-1724860350000",
      "title": "MINISTERO DELL'AGRICOLTURA, DELLA SOVRANITA' ALIMENTARE E DELLE FORESTE - DECRETO 30 luglio 2024",
      "link": "http://www.gazzettaufficiale.it/eli/id/2024/08/28/24A04435/SG",
      "published": "2024-08-28T15:52:30.000Z",
      "description": "Modifica del decreto  13  febbraio  2018,  n.  617,  recante:  «Nuove disposizioni nazionali in materia di riconoscimento e controllo delle organizzazioni di produttori del settore dell'olio  d'oliva  e  delle olive da tavola e loro associazioni»...."
    },
    {
      "id": "ys6k33-1724860350000",
      "title": "MINISTERO DELL'AGRICOLTURA, DELLA SOVRANITA' ALIMENTARE E DELLE FORESTE - DECRETO 31 luglio 2024",
      "link": "http://www.gazzettaufficiale.it/eli/id/2024/08/28/24A04422/SG",
      "published": "2024-08-28T15:52:30.000Z",
      "description": "Modifica    del    decreto    23    dicembre    2022    relativamente all'ammissibilita' dei prati montani con prevalenza di  tare  sparse. (24A04422)"
    },
    {
      "id": "z5vhyj-1724860348000",
      "title": "MINISTERO DELLE IMPRESE E DEL MADE IN ITALY - DECRETO 12 agosto 2024",
      "link": "http://www.gazzettaufficiale.it/eli/id/2024/08/28/24A04385/SG",
      "published": "2024-08-28T15:52:28.000Z",
      "description": "Liquidazione coatta amministrativa della «Servizi  e  Trasporti  2000 societa' cooperativa denominazione  abbreviata  Servizi  e  Trasporti 2000 soc. coop.», in Cagliari e nomina del  commissario  liquidatore. (24A04385)"
    },
    {
      "id": "yt9iaa-1724860350000",
      "title": "AGENZIA ITALIANA DEL FARMACO - COMUNICATO",
      "link": "http://www.gazzettaufficiale.it/eli/id/2024/08/28/24A04403/SG",
      "published": "2024-08-28T15:52:30.000Z",
      "description": "Autorizzazione all'immissione in commercio  del  medicinale  per  uso umano, a base di pazopanib, «Pazopanib Mylan» (24A04403)"
    },
    {
      "id": "z5u7zh-1724860348000",
      "title": "MINISTERO DELL'INTERNO - COMUNICATO",
      "link": "http://www.gazzettaufficiale.it/eli/id/2024/08/28/24A04387/SG",
      "published": "2024-08-28T15:52:28.000Z",
      "description": "Nomina della commissione straordinaria di liquidazione  cui  affidare la  gestione  del  dissesto  finanziario  del  Comune   di   Scordia. (24A04387)"
    },
    {
      "id": "z5tkzy-1724860348000",
      "title": "MINISTERO DELL'INTERNO - COMUNICATO",
      "link": "http://www.gazzettaufficiale.it/eli/id/2024/08/28/24A04388/SG",
      "published": "2024-08-28T15:52:28.000Z",
      "description": "Nomina del commissario straordinario di liquidazione cui affidare  la gestione  del  dissesto  finanziario  del  Comune   di   Roccalumera. (24A04388)"
    },
    {
      "id": "z5sy0f-1724860349000",
      "title": "MINISTERO DELL'INTERNO - COMUNICATO",
      "link": "http://www.gazzettaufficiale.it/eli/id/2024/08/28/24A04389/SG",
      "published": "2024-08-28T15:52:29.000Z",
      "description": "Nomina della commissione straordinaria di liquidazione  cui  affidare la  gestione  del  dissesto  finanziario  del  Comune  di   Lusciano. (24A04389)"
    },
    {
      "id": "z5ewat-1724860349000",
      "title": "MINISTERO DELLA DIFESA - COMUNICATO",
      "link": "http://www.gazzettaufficiale.it/eli/id/2024/08/28/24A04390/SG",
      "published": "2024-08-28T15:52:29.000Z",
      "description": "Concessione della medaglia d'oro al merito aeronautico (24A04390)"
    },
    {
      "id": "z5e9ba-1724860349000",
      "title": "MINISTERO DELLA DIFESA - COMUNICATO",
      "link": "http://www.gazzettaufficiale.it/eli/id/2024/08/28/24A04391/SG",
      "published": "2024-08-28T15:52:29.000Z",
      "description": "Concessione della medaglia d'oro al merito aeronautico (24A04391)"
    },
    {
      "id": "z5dmbr-1724860349000",
      "title": "MINISTERO DELLA DIFESA - COMUNICATO",
      "link": "http://www.gazzettaufficiale.it/eli/id/2024/08/28/24A04392/SG",
      "published": "2024-08-28T15:52:29.000Z",
      "description": "Concessione della medaglia d'oro al merito aeronautico (24A04392)"
    },
    {
      "id": "z5czc8-1724860349000",
      "title": "MINISTERO DELLA DIFESA - COMUNICATO",
      "link": "http://www.gazzettaufficiale.it/eli/id/2024/08/28/24A04393/SG",
      "published": "2024-08-28T15:52:29.000Z",
      "description": "Concessione della medaglia d'oro al merito aeronautico (24A04393)"
    },
    {
      "id": "yta59t-1724860349000",
      "title": "MINISTERO DELLA DIFESA - COMUNICATO",
      "link": "http://www.gazzettaufficiale.it/eli/id/2024/08/28/24A04402/SG",
      "published": "2024-08-28T15:52:29.000Z",
      "description": "Rettifica di  una  concessione  di  medaglia  al  valore  aeronautico (24A04402)"
    },
    {
      "id": "yb4xow-1724860351000",
      "title": "",
      "link": "http://www.gazzettaufficiale.it/eli/id/2024/08/28/24A04522/SG",
      "published": "2024-08-28T15:52:31.000Z",
      "description": "Comunicato relativo al  decreto  del  Presidente  del  Consiglio  dei ministri  2  agosto  2024,   recante:   «Piano   nazionale   per   la riqualificazione dei piccoli comuni - Approvazione  graduatoria  enti ammessi  al  finanziamento  ed ..."
    }
  ]
}