{
  "title": "Gazzetta Ufficiale - Serie Generale - Sommario",
  "link": "http://www.gazzettaufficiale.it/eli/gu/2024/08/01/179/SG/html",
  "description": "Gazzetta Ufficiale - Serie Generale n. 179 del 01-08-2024",
  "language": "it",
  "generator": "",
  "published": "",
  "entries": [
    {
      "id": "e0fuun-1722529963000",
      "title": "DELIBERA DEL CONSIGLIO DEI MINISTRI 22 luglio 2024",
      "link": "http://www.gazzettaufficiale.it/eli/id/2024/08/01/24A04023/SG",
      "published": "2024-08-01T16:32:43.000Z",
      "description": "Precisazione dell'estensione territoriale dello stato di emergenza in conseguenza degli eccezionali eventi meteorologici  verificatisi  nei giorni dal 15 maggio al 4 giugno 2024, di cui della delibera 3 luglio 2024, che  ricomprende  i  territori ..."
    },
    {
      "id": "e0ghu6-1722529963000",
      "title": "DELIBERA DEL CONSIGLIO DEI MINISTRI 22 luglio 2024",
      "link": "http://www.gazzettaufficiale.it/eli/id/2024/08/01/24A04024/SG",
      "published": "2024-08-01T16:32:43.000Z",
      "description": "Proroga dello stato di emergenza  in  conseguenza  degli  eccezionali eventi meteorologici verificatisi nei giorni 9 e 10 febbraio 2023 nel territorio dei liberi consorzi di Ragusa e di Siracusa, della  Citta' metropolitana di Catania e  dei ..."
    },
    {
      "id": "e0h4tp-1722529964000",
      "title": "DELIBERA DEL CONSIGLIO DEI MINISTRI 22 luglio 2024",
      "link": "http://www.gazzettaufficiale.it/eli/id/2024/08/01/24A04025/SG",
      "published": "2024-08-01T16:32:44.000Z",
      "description": "Dichiarazione  dello  stato  di  emergenza   in   conseguenza   degli eccezionali eventi meteorologici verificatisi  nel  territorio  della Regione autonoma Valle d'Aosta  nei  giorni  29  e  30  giugno  2024. (24A04025)"
    },
    {
      "id": "dzusa8-1722529958000",
      "title": "MINISTERO DELL'AGRICOLTURA, DELLA SOVRANITA' ALIMENTARE E DELLE FORESTE - DECRETO 19 luglio 2024",
      "link": "http://www.gazzettaufficiale.it/eli/id/2024/08/01/24A04011/SG",
      "published": "2024-08-01T16:32:38.000Z",
      "description": "Riconoscimento dell'idoneita' al Centro di saggio «AGRIN Soc. Cons. a r.l.» ad  effettuare  prove  ufficiali  di  campo,  finalizzate  alla produzione di dati di efficacia di prodotti fitosanitari. (24A04011)"
    },
    {
      "id": "dzvf9r-1722529958000",
      "title": "MINISTERO DELL'AGRICOLTURA, DELLA SOVRANITA' ALIMENTARE E DELLE FORESTE - DECRETO 19 luglio 2024",
      "link": "http://www.gazzettaufficiale.it/eli/id/2024/08/01/24A04012/SG",
      "published": "2024-08-01T16:32:38.000Z",
      "description": "Riconoscimento  dell'idoneita'  al  Centro  di  saggio   «Cooperativa Terremerse» ad effettuare prove ufficiali di campo, finalizzate  alla produzione di dati di efficacia di prodotti fitosanitari. (24A04012)"
    },
    {
      "id": "3nm2kr-1722529951000",
      "title": "PRESIDENZA DEL CONSIGLIO DEI MINISTRI DIPARTIMENTO DELLA PROTEZIONE CIVILE - DECRETO 8 maggio 2024",
      "link": "http://www.gazzettaufficiale.it/eli/id/2024/08/01/24A03961/SG",
      "published": "2024-08-01T16:32:31.000Z",
      "description": "Caratteristiche delle insegne, criteri di conferimento e  aspetti  di natura procedurale relativi alle attestazioni di pubblica benemerenza del Dipartimento della protezione civile. (24A03961)"
    },
    {
      "id": "3m1vqb-1722529948000",
      "title": "AGENZIA ITALIANA DEL FARMACO - DETERMINA 9 luglio 2024",
      "link": "http://www.gazzettaufficiale.it/eli/id/2024/08/01/24A03936/SG",
      "published": "2024-08-01T16:32:28.000Z",
      "description": "Riclassificazione del medicinale per uso umano  «Finasteride  Alter», ai sensi dell'articolo 8, comma 10, della legge 24 dicembre 1993,  n. 537. (Determina n. 205/2024). (24A03936)"
    },
    {
      "id": "3m2ipu-1722529949000",
      "title": "AGENZIA ITALIANA DEL FARMACO - DETERMINA 9 luglio 2024",
      "link": "http://www.gazzettaufficiale.it/eli/id/2024/08/01/24A03937/SG",
      "published": "2024-08-01T16:32:29.000Z",
      "description": "Riclassificazione del medicinale per uso umano  «Lytgobi»,  ai  sensi dell'articolo 8, comma 10, della legge  24  dicembre  1993,  n.  537. (Determina n. 206/2024). (24A03937)"
    },
    {
      "id": "3m35pd-1722529949000",
      "title": "AGENZIA ITALIANA DEL FARMACO - DETERMINA 9 luglio 2024",
      "link": "http://www.gazzettaufficiale.it/eli/id/2024/08/01/24A03938/SG",
      "published": "2024-08-01T16:32:29.000Z",
      "description": "Riclassificazione del medicinale per uso umano  «Fosamax»,  ai  sensi dell'articolo 8, comma 10, della legge  24  dicembre  1993,  n.  537. (Determina n. 207/2024). (24A03938)"
    },
    {
      "id": "3m3sow-1722529950000",
      "title": "AGENZIA ITALIANA DEL FARMACO - DETERMINA 9 luglio 2024",
      "link": "http://www.gazzettaufficiale.it/eli/id/2024/08/01/24A03939/SG",
      "published": "2024-08-01T16:32:30.000Z",
      "description": "Riclassificazione del medicinale per uso umano «Fosavance», ai  sensi dell'articolo 8, comma 10, della legge  24  dicembre  1993,  n.  537. (Determina n. 208/2024). (24A03939)"
    },
    {
      "id": "379co5-1722529945000",
      "title": "AGENZIA ITALIANA DEL FARMACO - COMUNICATO",
      "link": "http://www.gazzettaufficiale.it/eli/id/2024/08/01/24A03879/SG",
      "published": "2024-08-01T16:32:25.000Z",
      "description": "Autorizzazione all'importazione  parallela  del  medicinale  per  uso umano «Aclasta» (24A03879)"
    },
    {
      "id": "37nedr-1722529946000",
      "title": "AGENZIA ITALIANA DEL FARMACO - COMUNICATO",
      "link": "http://www.gazzettaufficiale.it/eli/id/2024/08/01/24A03880/SG",
      "published": "2024-08-01T16:32:26.000Z",
      "description": "Autorizzazione all'importazione  parallela  del  medicinale  per  uso umano «Minoxidil Bailleul» (24A03880)"
    },
    {
      "id": "37o1da-1722529946000",
      "title": "AGENZIA ITALIANA DEL FARMACO - COMUNICATO",
      "link": "http://www.gazzettaufficiale.it/eli/id/2024/08/01/24A03881/SG",
      "published": "2024-08-01T16:32:26.000Z",
      "description": "Autorizzazione all'importazione  parallela  del  medicinale  per  uso umano «Arimidex» (24A03881)"
    },
    {
      "id": "37ooct-1722529947000",
      "title": "AGENZIA ITALIANA DEL FARMACO - COMUNICATO",
      "link": "http://www.gazzettaufficiale.it/eli/id/2024/08/01/24A03882/SG",
      "published": "2024-08-01T16:32:27.000Z",
      "description": "Autorizzazione all'importazione  parallela  del  medicinale  per  uso umano «Malarone» (24A03882)"
    },
    {
      "id": "37pbcc-1722529947000",
      "title": "AGENZIA ITALIANA DEL FARMACO - COMUNICATO",
      "link": "http://www.gazzettaufficiale.it/eli/id/2024/08/01/24A03883/SG",
      "published": "2024-08-01T16:32:27.000Z",
      "description": "Autorizzazione all'importazione  parallela  del  medicinale  per  uso umano «Spasmomen» (24A03883)"
    },
    {
      "id": "3mhuei-1722529951000",
      "title": "AGENZIA ITALIANA DEL FARMACO - COMUNICATO",
      "link": "http://www.gazzettaufficiale.it/eli/id/2024/08/01/24A03940/SG",
      "published": "2024-08-01T16:32:31.000Z",
      "description": "Revoca, su rinuncia, dell'autorizzazione all'immissione in  commercio del medicinale per uso umano «Niaouli Essenza Farmakopea». (24A03940)"
    },
    {
      "id": "dzw29a-1722529959000",
      "title": "AGENZIA ITALIANA DEL FARMACO - COMUNICATO",
      "link": "http://www.gazzettaufficiale.it/eli/id/2024/08/01/24A04013/SG",
      "published": "2024-08-01T16:32:39.000Z",
      "description": "Sospensione  dell'autorizzazione  all'immissione  in  commercio   del medicinale per uso umano, a base  di  amiloride  e  idroclorotiazide, «Amiloride e Idroclorotiazide Aurobindo». (24A04013)"
    },
    {
      "id": "dzwp8t-1722529960000",
      "title": "MINISTERO DEGLI AFFARI ESTERI E DELLA COOPERAZIONE INTERNAZIONALE - COMUNICATO",
      "link": "http://www.gazzettaufficiale.it/eli/id/2024/08/01/24A04014/SG",
      "published": "2024-08-01T16:32:40.000Z",
      "description": "Rilascio di exequatur (24A04014)"
    },
    {
      "id": "dzxc8c-1722529960000",
      "title": "MINISTERO DEGLI AFFARI ESTERI E DELLA COOPERAZIONE INTERNAZIONALE - COMUNICATO",
      "link": "http://www.gazzettaufficiale.it/eli/id/2024/08/01/24A04015/SG",
      "published": "2024-08-01T16:32:40.000Z",
      "description": "Rilascio di exequatur (24A04015)"
    },
    {
      "id": "dzxz7v-1722529961000",
      "title": "MINISTERO DELL'ECONOMIA E DELLE FINANZE - COMUNICATO",
      "link": "http://www.gazzettaufficiale.it/eli/id/2024/08/01/24A04016/SG",
      "published": "2024-08-01T16:32:41.000Z",
      "description": "Cambi di riferimento rilevati  a  titolo  indicativo  del  giorno  15 luglio 2024 (24A04016)"
    },
    {
      "id": "dzym7e-1722529961000",
      "title": "MINISTERO DELL'ECONOMIA E DELLE FINANZE - COMUNICATO",
      "link": "http://www.gazzettaufficiale.it/eli/id/2024/08/01/24A04017/SG",
      "published": "2024-08-01T16:32:41.000Z",
      "description": "Cambi di riferimento rilevati  a  titolo  indicativo  del  giorno  16 luglio 2024 (24A04017)"
    },
    {
      "id": "dzz96x-1722529961000",
      "title": "MINISTERO DELL'ECONOMIA E DELLE FINANZE - COMUNICATO",
      "link": "http://www.gazzettaufficiale.it/eli/id/2024/08/01/24A04018/SG",
      "published": "2024-08-01T16:32:41.000Z",
      "description": "Cambi di riferimento rilevati  a  titolo  indicativo  del  giorno  17 luglio 2024 (24A04018)"
    },
    {
      "id": "dzzw6g-1722529962000",
      "title": "MINISTERO DELL'ECONOMIA E DELLE FINANZE - COMUNICATO",
      "link": "http://www.gazzettaufficiale.it/eli/id/2024/08/01/24A04019/SG",
      "published": "2024-08-01T16:32:42.000Z",
      "description": "Cambi di riferimento rilevati  a  titolo  indicativo  del  giorno  18 luglio 2024 (24A04019)"
    },
    {
      "id": "e0dxw2-1722529962000",
      "title": "MINISTERO DELL'ECONOMIA E DELLE FINANZE - COMUNICATO",
      "link": "http://www.gazzettaufficiale.it/eli/id/2024/08/01/24A04020/SG",
      "published": "2024-08-01T16:32:42.000Z",
      "description": "Cambi di riferimento rilevati  a  titolo  indicativo  del  giorno  19 luglio 2024 (24A04020)"
    },
    {
      "id": "3nmpka-1722529954000",
      "title": "MINISTERO DELL'INTERNO - COMUNICATO",
      "link": "http://www.gazzettaufficiale.it/eli/id/2024/08/01/24A03962/SG",
      "published": "2024-08-01T16:32:34.000Z",
      "description": "Riconoscimento e classificazione di un prodotto esplosivo (24A03962)"
    },
    {
      "id": "3nncjt-1722529954000",
      "title": "MINISTERO DELL'INTERNO - COMUNICATO",
      "link": "http://www.gazzettaufficiale.it/eli/id/2024/08/01/24A03963/SG",
      "published": "2024-08-01T16:32:34.000Z",
      "description": "Classificazione di un prodotto esplosivo (24A03963)"
    },
    {
      "id": "3nnzjc-1722529955000",
      "title": "MINISTERO DELL'INTERNO - COMUNICATO",
      "link": "http://www.gazzettaufficiale.it/eli/id/2024/08/01/24A03964/SG",
      "published": "2024-08-01T16:32:35.000Z",
      "description": "Riconoscimento  e  classificazione  di  alcuni   prodotti   esplosivi (24A03964)"
    },
    {
      "id": "3nomiv-1722529955000",
      "title": "MINISTERO DELL'INTERNO - COMUNICATO",
      "link": "http://www.gazzettaufficiale.it/eli/id/2024/08/01/24A03965/SG",
      "published": "2024-08-01T16:32:35.000Z",
      "description": "Riconoscimento  e  classificazione  di  alcuni   prodotti   esplosivi (24A03965)"
    },
    {
      "id": "3np9ie-1722529956000",
      "title": "MINISTERO DELL'INTERNO - COMUNICATO",
      "link": "http://www.gazzettaufficiale.it/eli/id/2024/08/01/24A03966/SG",
      "published": "2024-08-01T16:32:36.000Z",
      "description": "Riconoscimento  e  classificazione  di  alcuni   prodotti   esplosivi (24A03966)"
    },
    {
      "id": "3npwhx-1722529956000",
      "title": "MINISTERO DELL'INTERNO - COMUNICATO",
      "link": "http://www.gazzettaufficiale.it/eli/id/2024/08/01/24A03967/SG",
      "published": "2024-08-01T16:32:36.000Z",
      "description": "Classificazione di un prodotto esplosivo (24A03967)"
    },
    {
      "id": "3nqjhg-1722529957000",
      "title": "MINISTERO DELL'INTERNO - COMUNICATO",
      "link": "http://www.gazzettaufficiale.it/eli/id/2024/08/01/24A03968/SG",
      "published": "2024-08-01T16:32:37.000Z",
      "description": "Soppressione  dell'Arciconfraternita  dell'Immacolata  Concezione   a Pontenuovo, in Napoli (24A03968)"
    },
    {
      "id": "3nr6gz-1722529957000",
      "title": "MINISTERO DELL'INTERNO - COMUNICATO",
      "link": "http://www.gazzettaufficiale.it/eli/id/2024/08/01/24A03969/SG",
      "published": "2024-08-01T16:32:37.000Z",
      "description": "Mutamento della denominazione assunta dalla Fondazione  di  religione «Ente diocesano per le Opere di  culto  e  religione»,  in  Pescia  e contestuale trasferimento della sede. (24A03969)"
    },
    {
      "id": "3o586l-1722529957000",
      "title": "MINISTERO DELL'INTERNO - COMUNICATO",
      "link": "http://www.gazzettaufficiale.it/eli/id/2024/08/01/24A03970/SG",
      "published": "2024-08-01T16:32:37.000Z",
      "description": "Fusione per incorporazione dell'Istituto delle Maestre Pie  Filippini di Montefiascone in  Montefiascone,  nel  Pontificio  Istituto  delle Maestre Pie Filippini, in Roma. (24A03970)"
    }
  ]
}